{
  "updated": "2026-07-04T23:31:40.710376",
  "incidents": [
    {
      "date": "2026-07-02",
      "lat": 2.1786,
      "lng": 101.4378,
      "type": "Theft",
      "region": "Strait of Malacca",
      "description": "Stores stolen from deck during hours of darkness.",
      "reference": "REF-20260702-009"
    },
    {
      "date": "2026-06-30",
      "lat": 2.2981,
      "lng": 5.493,
      "type": "Kidnapping",
      "region": "Gulf of Guinea",
      "description": "Crew members taken. Authorities notified.",
      "reference": "REF-20260630-012"
    },
    {
      "date": "2026-06-26",
      "lat": 11.3484,
      "lng": 45.2487,
      "type": "Armed Robbery",
      "region": "Gulf of Aden",
      "description": "Unauthorized boarding while at anchor. Items stolen from deck.",
      "reference": "REF-20260626-017"
    },
    {
      "date": "2026-06-18",
      "lat": 11.6988,
      "lng": 110.1089,
      "type": "Suspicious Activity",
      "region": "South China Sea",
      "description": "Maritime security incident reported.",
      "reference": "REF-20260618-005"
    },
    {
      "date": "2026-06-13",
      "lat": 3.84,
      "lng": 9.3258,
      "type": "Kidnapping",
      "region": "Nigeria Coast",
      "description": "Crew members taken. Authorities notified.",
      "reference": "REF-20260613-002"
    },
    {
      "date": "2026-06-12",
      "lat": 16.0608,
      "lng": 42.7059,
      "type": "Warning Shots",
      "region": "Red Sea",
      "description": "Warning shots fired across bow.",
      "reference": "REF-20260612-010"
    },
    {
      "date": "2026-06-07",
      "lat": 8.7214,
      "lng": 110.0457,
      "type": "Suspicious Activity",
      "region": "South China Sea",
      "description": "Maritime security incident reported.",
      "reference": "REF-20260607-018"
    },
    {
      "date": "2026-06-06",
      "lat": 2.1536,
      "lng": 105.0634,
      "type": "Theft",
      "region": "Singapore Strait",
      "description": "Stores stolen from deck during hours of darkness.",
      "reference": "REF-20260606-013"
    },
    {
      "date": "2026-06-06",
      "lat": 4.0669,
      "lng": 103.8287,
      "type": "Theft",
      "region": "Strait of Malacca",
      "description": "Stores stolen from deck during hours of darkness.",
      "reference": "REF-20260606-016"
    },
    {
      "date": "2026-05-31",
      "lat": 2.8223,
      "lng": 98.2759,
      "type": "Theft",
      "region": "Strait of Malacca",
      "description": "Stores stolen from deck during hours of darkness.",
      "reference": "REF-20260531-001"
    },
    {
      "date": "2026-05-22",
      "lat": 4.0343,
      "lng": 8.3722,
      "type": "Armed Robbery",
      "region": "Nigeria Coast",
      "description": "Unauthorized boarding while at anchor. Items stolen from deck.",
      "reference": "REF-20260522-015"
    },
    {
      "date": "2026-05-21",
      "lat": 4.3698,
      "lng": 50.2944,
      "type": "Piracy",
      "region": "Somalia Coast",
      "description": "Vessel approached by armed skiffs. Evasive maneuvers taken.",
      "reference": "REF-20260521-006"
    },
    {
      "date": "2026-05-20",
      "lat": 1.4744,
      "lng": 100.2243,
      "type": "Theft",
      "region": "Strait of Malacca",
      "description": "Stores stolen from deck during hours of darkness.",
      "reference": "REF-20260520-014"
    },
    {
      "date": "2026-05-15",
      "lat": 6.1076,
      "lng": 52.0236,
      "type": "Piracy",
      "region": "Somalia Coast",
      "description": "Vessel approached by armed skiffs. Evasive maneuvers taken.",
      "reference": "REF-20260515-011"
    },
    {
      "date": "2026-05-13",
      "lat": 6.0745,
      "lng": 49.3963,
      "type": "Piracy",
      "region": "Somalia Coast",
      "description": "Vessel approached by armed skiffs. Evasive maneuvers taken.",
      "reference": "REF-20260513-008"
    },
    {
      "date": "2026-05-10",
      "lat": 4.7085,
      "lng": 52.248,
      "type": "Piracy",
      "region": "Somalia Coast",
      "description": "Vessel approached by armed skiffs. Evasive maneuvers taken.",
      "reference": "REF-20260510-004"
    },
    {
      "date": "2026-05-08",
      "lat": 4.9854,
      "lng": 47.0023,
      "type": "Hijacking",
      "region": "Somalia Coast",
      "description": "Vessel boarded and taken control of by armed persons.",
      "reference": "REF-20260508-003"
    },
    {
      "date": "2026-05-08",
      "lat": 5.3423,
      "lng": 6.1934,
      "type": "Armed Robbery",
      "region": "Gulf of Guinea",
      "description": "Unauthorized boarding while at anchor. Items stolen from deck.",
      "reference": "REF-20260508-007"
    }
  ],
  "source": "Maritime Security Hotspot Data"
}