{
  "updated": "2026-04-02T23:46:43.367140",
  "incidents": [
    {
      "date": "2026-03-29",
      "lat": 9.2843,
      "lng": 113.8988,
      "type": "Suspicious Activity",
      "region": "South China Sea",
      "description": "Maritime security incident reported.",
      "reference": "REF-20260329-006"
    },
    {
      "date": "2026-03-29",
      "lat": 6.3066,
      "lng": 6.3509,
      "type": "Kidnapping",
      "region": "Nigeria Coast",
      "description": "Crew members taken. Authorities notified.",
      "reference": "REF-20260329-012"
    },
    {
      "date": "2026-03-23",
      "lat": 8.5779,
      "lng": 114.756,
      "type": "Harassment",
      "region": "South China Sea",
      "description": "Vessel harassed by military/paramilitary craft.",
      "reference": "REF-20260323-002"
    },
    {
      "date": "2026-03-20",
      "lat": 16.5715,
      "lng": 41.7615,
      "type": "Warning Shots",
      "region": "Red Sea",
      "description": "Warning shots fired across bow.",
      "reference": "REF-20260320-003"
    },
    {
      "date": "2026-03-18",
      "lat": 16.5641,
      "lng": 37.8248,
      "type": "Warning Shots",
      "region": "Red Sea",
      "description": "Warning shots fired across bow.",
      "reference": "REF-20260318-005"
    },
    {
      "date": "2026-03-18",
      "lat": 6.0325,
      "lng": 51.814,
      "type": "Hijacking",
      "region": "Somalia Coast",
      "description": "Vessel boarded and taken control of by armed persons.",
      "reference": "REF-20260318-015"
    },
    {
      "date": "2026-03-15",
      "lat": 10.3268,
      "lng": 109.983,
      "type": "Suspicious Activity",
      "region": "South China Sea",
      "description": "Maritime security incident reported.",
      "reference": "REF-20260315-017"
    },
    {
      "date": "2026-03-14",
      "lat": 3.127,
      "lng": 105.4733,
      "type": "Boarding",
      "region": "Singapore Strait",
      "description": "Unauthorized persons boarded vessel.",
      "reference": "REF-20260314-016"
    },
    {
      "date": "2026-03-12",
      "lat": 8.0157,
      "lng": 109.4574,
      "type": "Harassment",
      "region": "South China Sea",
      "description": "Vessel harassed by military/paramilitary craft.",
      "reference": "REF-20260312-013"
    },
    {
      "date": "2026-03-12",
      "lat": 6.0168,
      "lng": 9.3838,
      "type": "Armed Robbery",
      "region": "Nigeria Coast",
      "description": "Unauthorized boarding while at anchor. Items stolen from deck.",
      "reference": "REF-20260312-018"
    },
    {
      "date": "2026-03-11",
      "lat": 3.0935,
      "lng": 6.1196,
      "type": "Armed Robbery",
      "region": "Nigeria Coast",
      "description": "Unauthorized boarding while at anchor. Items stolen from deck.",
      "reference": "REF-20260311-009"
    },
    {
      "date": "2026-03-07",
      "lat": 9.9008,
      "lng": 112.012,
      "type": "Harassment",
      "region": "South China Sea",
      "description": "Vessel harassed by military/paramilitary craft.",
      "reference": "REF-20260307-004"
    },
    {
      "date": "2026-02-26",
      "lat": 6.7802,
      "lng": 48.8452,
      "type": "Piracy",
      "region": "Somalia Coast",
      "description": "Vessel approached by armed skiffs. Evasive maneuvers taken.",
      "reference": "REF-20260226-010"
    },
    {
      "date": "2026-02-20",
      "lat": 5.1633,
      "lng": 5.8607,
      "type": "Kidnapping",
      "region": "Nigeria Coast",
      "description": "Crew members taken. Authorities notified.",
      "reference": "REF-20260220-007"
    },
    {
      "date": "2026-02-14",
      "lat": 13.4378,
      "lng": 41.7972,
      "type": "Suspicious Approach",
      "region": "Red Sea",
      "description": "Unknown vessels approached at high speed. Watchkeeping increased.",
      "reference": "REF-20260214-014"
    },
    {
      "date": "2026-02-12",
      "lat": 5.1576,
      "lng": 5.8936,
      "type": "Kidnapping",
      "region": "Gulf of Guinea",
      "description": "Crew members taken. Authorities notified.",
      "reference": "REF-20260212-011"
    },
    {
      "date": "2026-02-08",
      "lat": 16.9818,
      "lng": 39.6296,
      "type": "Warning Shots",
      "region": "Red Sea",
      "description": "Warning shots fired across bow.",
      "reference": "REF-20260208-008"
    },
    {
      "date": "2026-02-03",
      "lat": 2.568,
      "lng": 101.294,
      "type": "Theft",
      "region": "Singapore Strait",
      "description": "Stores stolen from deck during hours of darkness.",
      "reference": "REF-20260203-001"
    }
  ],
  "source": "Maritime Security Hotspot Data"
}