{
  "updated": "2026-04-24T21:51:03.578174",
  "incidents": [
    {
      "date": "2026-04-23",
      "lat": 3.9221,
      "lng": 8.3076,
      "type": "Kidnapping",
      "region": "Nigeria Coast",
      "description": "Crew members taken. Authorities notified.",
      "reference": "REF-20260423-006"
    },
    {
      "date": "2026-04-20",
      "lat": 6.7284,
      "lng": 52.0509,
      "type": "Piracy",
      "region": "Somalia Coast",
      "description": "Vessel approached by armed skiffs. Evasive maneuvers taken.",
      "reference": "REF-20260420-014"
    },
    {
      "date": "2026-04-14",
      "lat": 11.3614,
      "lng": 110.9419,
      "type": "Harassment",
      "region": "South China Sea",
      "description": "Vessel harassed by military/paramilitary craft.",
      "reference": "REF-20260414-009"
    },
    {
      "date": "2026-04-12",
      "lat": 3.0655,
      "lng": 4.0972,
      "type": "Armed Robbery",
      "region": "Nigeria Coast",
      "description": "Unauthorized boarding while at anchor. Items stolen from deck.",
      "reference": "REF-20260412-010"
    },
    {
      "date": "2026-04-11",
      "lat": -0.4505,
      "lng": 104.0334,
      "type": "Boarding",
      "region": "Singapore Strait",
      "description": "Unauthorized persons boarded vessel.",
      "reference": "REF-20260411-005"
    },
    {
      "date": "2026-04-06",
      "lat": 9.4391,
      "lng": 113.4966,
      "type": "Suspicious Activity",
      "region": "South China Sea",
      "description": "Maritime security incident reported.",
      "reference": "REF-20260406-002"
    },
    {
      "date": "2026-04-02",
      "lat": 4.3455,
      "lng": 100.6659,
      "type": "Armed Robbery",
      "region": "Strait of Malacca",
      "description": "Unauthorized boarding while at anchor. Items stolen from deck.",
      "reference": "REF-20260402-020"
    },
    {
      "date": "2026-03-29",
      "lat": 0.2295,
      "lng": 104.5356,
      "type": "Boarding",
      "region": "Singapore Strait",
      "description": "Unauthorized persons boarded vessel.",
      "reference": "REF-20260329-016"
    },
    {
      "date": "2026-03-27",
      "lat": -0.5029,
      "lng": 105.7138,
      "type": "Theft",
      "region": "Singapore Strait",
      "description": "Stores stolen from deck during hours of darkness.",
      "reference": "REF-20260327-004"
    },
    {
      "date": "2026-03-24",
      "lat": 8.9767,
      "lng": 110.2247,
      "type": "Suspicious Activity",
      "region": "South China Sea",
      "description": "Maritime security incident reported.",
      "reference": "REF-20260324-011"
    },
    {
      "date": "2026-03-24",
      "lat": 1.6792,
      "lng": 102.4027,
      "type": "Boarding",
      "region": "Singapore Strait",
      "description": "Unauthorized persons boarded vessel.",
      "reference": "REF-20260324-019"
    },
    {
      "date": "2026-03-22",
      "lat": 7.7618,
      "lng": 50.6832,
      "type": "Piracy",
      "region": "Somalia Coast",
      "description": "Vessel approached by armed skiffs. Evasive maneuvers taken.",
      "reference": "REF-20260322-003"
    },
    {
      "date": "2026-03-17",
      "lat": 8.2519,
      "lng": 114.019,
      "type": "Suspicious Activity",
      "region": "South China Sea",
      "description": "Maritime security incident reported.",
      "reference": "REF-20260317-018"
    },
    {
      "date": "2026-03-16",
      "lat": 5.2074,
      "lng": 52.9936,
      "type": "Hijacking",
      "region": "Somalia Coast",
      "description": "Vessel boarded and taken control of by armed persons.",
      "reference": "REF-20260316-012"
    },
    {
      "date": "2026-03-07",
      "lat": 14.6907,
      "lng": 37.9432,
      "type": "Suspicious Approach",
      "region": "Red Sea",
      "description": "Unknown vessels approached at high speed. Watchkeeping increased.",
      "reference": "REF-20260307-008"
    },
    {
      "date": "2026-03-06",
      "lat": 1.6115,
      "lng": 102.2015,
      "type": "Boarding",
      "region": "Singapore Strait",
      "description": "Unauthorized persons boarded vessel.",
      "reference": "REF-20260306-017"
    },
    {
      "date": "2026-03-05",
      "lat": 14.4408,
      "lng": 46.9988,
      "type": "Piracy",
      "region": "Gulf of Aden",
      "description": "Vessel approached by armed skiffs. Evasive maneuvers taken.",
      "reference": "REF-20260305-007"
    },
    {
      "date": "2026-03-04",
      "lat": 12.7118,
      "lng": 47.6292,
      "type": "Suspicious Approach",
      "region": "Gulf of Aden",
      "description": "Unknown vessels approached at high speed. Watchkeeping increased.",
      "reference": "REF-20260304-001"
    },
    {
      "date": "2026-03-01",
      "lat": 2.197,
      "lng": 99.4273,
      "type": "Theft",
      "region": "Strait of Malacca",
      "description": "Stores stolen from deck during hours of darkness.",
      "reference": "REF-20260301-013"
    },
    {
      "date": "2026-02-24",
      "lat": 2.3178,
      "lng": 7.3922,
      "type": "Kidnapping",
      "region": "Gulf of Guinea",
      "description": "Crew members taken. Authorities notified.",
      "reference": "REF-20260224-015"
    }
  ],
  "source": "Maritime Security Hotspot Data"
}