{
  "updated": "2026-03-03T05:06:14.238164",
  "incidents": [
    {
      "date": "2026-03-02",
      "lat": 5.4413,
      "lng": 2.0032,
      "type": "Kidnapping",
      "region": "Gulf of Guinea",
      "description": "Crew members taken. Authorities notified.",
      "reference": "REF-20260302-015"
    },
    {
      "date": "2026-03-02",
      "lat": 10.5289,
      "lng": 114.3473,
      "type": "Suspicious Activity",
      "region": "South China Sea",
      "description": "Maritime security incident reported.",
      "reference": "REF-20260302-022"
    },
    {
      "date": "2026-03-02",
      "lat": 4.8729,
      "lng": 4.3187,
      "type": "Kidnapping",
      "region": "Gulf of Guinea",
      "description": "Crew members taken. Authorities notified.",
      "reference": "REF-20260302-024"
    },
    {
      "date": "2026-03-01",
      "lat": 0.6114,
      "lng": 102.5924,
      "type": "Theft",
      "region": "Singapore Strait",
      "description": "Stores stolen from deck during hours of darkness.",
      "reference": "REF-20260301-014"
    },
    {
      "date": "2026-03-01",
      "lat": 10.9077,
      "lng": 109.7362,
      "type": "Suspicious Activity",
      "region": "South China Sea",
      "description": "Maritime security incident reported.",
      "reference": "REF-20260301-023"
    },
    {
      "date": "2026-02-26",
      "lat": 13.9105,
      "lng": 38.2251,
      "type": "Warning Shots",
      "region": "Red Sea",
      "description": "Warning shots fired across bow.",
      "reference": "REF-20260226-013"
    },
    {
      "date": "2026-02-23",
      "lat": 2.2826,
      "lng": 103.92,
      "type": "Armed Robbery",
      "region": "Strait of Malacca",
      "description": "Unauthorized boarding while at anchor. Items stolen from deck.",
      "reference": "REF-20260223-001"
    },
    {
      "date": "2026-02-16",
      "lat": 5.5581,
      "lng": 6.1947,
      "type": "Armed Robbery",
      "region": "Gulf of Guinea",
      "description": "Unauthorized boarding while at anchor. Items stolen from deck.",
      "reference": "REF-20260216-009"
    },
    {
      "date": "2026-02-14",
      "lat": 2.9693,
      "lng": 7.1758,
      "type": "Kidnapping",
      "region": "Gulf of Guinea",
      "description": "Crew members taken. Authorities notified.",
      "reference": "REF-20260214-016"
    },
    {
      "date": "2026-02-10",
      "lat": 3.4602,
      "lng": 102.9725,
      "type": "Armed Robbery",
      "region": "Strait of Malacca",
      "description": "Unauthorized boarding while at anchor. Items stolen from deck.",
      "reference": "REF-20260210-010"
    },
    {
      "date": "2026-02-04",
      "lat": 1.3514,
      "lng": 105.5212,
      "type": "Boarding",
      "region": "Singapore Strait",
      "description": "Unauthorized persons boarded vessel.",
      "reference": "REF-20260204-006"
    },
    {
      "date": "2026-02-02",
      "lat": 16.4994,
      "lng": 42.1791,
      "type": "Suspicious Approach",
      "region": "Red Sea",
      "description": "Unknown vessels approached at high speed. Watchkeeping increased.",
      "reference": "REF-20260202-004"
    },
    {
      "date": "2026-01-30",
      "lat": 8.4212,
      "lng": 113.7047,
      "type": "Suspicious Activity",
      "region": "South China Sea",
      "description": "Maritime security incident reported.",
      "reference": "REF-20260130-018"
    },
    {
      "date": "2026-01-28",
      "lat": 1.3178,
      "lng": 104.3848,
      "type": "Theft",
      "region": "Singapore Strait",
      "description": "Stores stolen from deck during hours of darkness.",
      "reference": "REF-20260128-019"
    },
    {
      "date": "2026-01-26",
      "lat": 14.9994,
      "lng": 39.1048,
      "type": "Warning Shots",
      "region": "Red Sea",
      "description": "Warning shots fired across bow.",
      "reference": "REF-20260126-008"
    },
    {
      "date": "2026-01-23",
      "lat": 2.7357,
      "lng": 6.5566,
      "type": "Armed Robbery",
      "region": "Nigeria Coast",
      "description": "Unauthorized boarding while at anchor. Items stolen from deck.",
      "reference": "REF-20260123-005"
    },
    {
      "date": "2026-01-21",
      "lat": 11.4724,
      "lng": 42.3659,
      "type": "Piracy",
      "region": "Gulf of Aden",
      "description": "Vessel approached by armed skiffs. Evasive maneuvers taken.",
      "reference": "REF-20260121-017"
    },
    {
      "date": "2026-01-20",
      "lat": 11.4488,
      "lng": 113.2865,
      "type": "Suspicious Activity",
      "region": "South China Sea",
      "description": "Maritime security incident reported.",
      "reference": "REF-20260120-003"
    },
    {
      "date": "2026-01-16",
      "lat": 14.0706,
      "lng": 38.795,
      "type": "Suspicious Approach",
      "region": "Red Sea",
      "description": "Unknown vessels approached at high speed. Watchkeeping increased.",
      "reference": "REF-20260116-012"
    },
    {
      "date": "2026-01-14",
      "lat": 15.0799,
      "lng": 37.7287,
      "type": "Suspicious Approach",
      "region": "Red Sea",
      "description": "Unknown vessels approached at high speed. Watchkeeping increased.",
      "reference": "REF-20260114-007"
    },
    {
      "date": "2026-01-14",
      "lat": 7.6885,
      "lng": 47.7717,
      "type": "Hijacking",
      "region": "Somalia Coast",
      "description": "Vessel boarded and taken control of by armed persons.",
      "reference": "REF-20260114-020"
    },
    {
      "date": "2026-01-11",
      "lat": 5.4627,
      "lng": 4.1098,
      "type": "Piracy",
      "region": "Gulf of Guinea",
      "description": "Vessel approached by armed skiffs. Evasive maneuvers taken.",
      "reference": "REF-20260111-021"
    },
    {
      "date": "2026-01-04",
      "lat": 5.4593,
      "lng": 8.3537,
      "type": "Armed Robbery",
      "region": "Nigeria Coast",
      "description": "Unauthorized boarding while at anchor. Items stolen from deck.",
      "reference": "REF-20260104-011"
    },
    {
      "date": "2026-01-03",
      "lat": 13.2671,
      "lng": 40.401,
      "type": "Warning Shots",
      "region": "Red Sea",
      "description": "Warning shots fired across bow.",
      "reference": "REF-20260103-002"
    }
  ],
  "source": "Maritime Security Hotspot Data"
}