{
  "updated": "2026-05-03T17:24:53.300781",
  "incidents": [
    {
      "date": "2026-04-27",
      "lat": 3.445,
      "lng": 5.9751,
      "type": "Kidnapping",
      "region": "Nigeria Coast",
      "description": "Crew members taken. Authorities notified.",
      "reference": "REF-20260427-002"
    },
    {
      "date": "2026-04-26",
      "lat": 10.5933,
      "lng": 45.7385,
      "type": "Piracy",
      "region": "Gulf of Aden",
      "description": "Vessel approached by armed skiffs. Evasive maneuvers taken.",
      "reference": "REF-20260426-013"
    },
    {
      "date": "2026-04-24",
      "lat": 2.4806,
      "lng": 102.7912,
      "type": "Theft",
      "region": "Strait of Malacca",
      "description": "Stores stolen from deck during hours of darkness.",
      "reference": "REF-20260424-007"
    },
    {
      "date": "2026-04-21",
      "lat": 0.8439,
      "lng": 103.1972,
      "type": "Boarding",
      "region": "Singapore Strait",
      "description": "Unauthorized persons boarded vessel.",
      "reference": "REF-20260421-009"
    },
    {
      "date": "2026-04-19",
      "lat": 3.8394,
      "lng": 102.8884,
      "type": "Armed Robbery",
      "region": "Strait of Malacca",
      "description": "Unauthorized boarding while at anchor. Items stolen from deck.",
      "reference": "REF-20260419-001"
    },
    {
      "date": "2026-04-18",
      "lat": 1.5008,
      "lng": 98.0558,
      "type": "Armed Robbery",
      "region": "Strait of Malacca",
      "description": "Unauthorized boarding while at anchor. Items stolen from deck.",
      "reference": "REF-20260418-015"
    },
    {
      "date": "2026-04-11",
      "lat": 4.4023,
      "lng": 47.498,
      "type": "Piracy",
      "region": "Somalia Coast",
      "description": "Vessel approached by armed skiffs. Evasive maneuvers taken.",
      "reference": "REF-20260411-011"
    },
    {
      "date": "2026-04-07",
      "lat": 5.7457,
      "lng": 50.935,
      "type": "Piracy",
      "region": "Somalia Coast",
      "description": "Vessel approached by armed skiffs. Evasive maneuvers taken.",
      "reference": "REF-20260407-016"
    },
    {
      "date": "2026-04-01",
      "lat": 4.4554,
      "lng": 103.0442,
      "type": "Armed Robbery",
      "region": "Strait of Malacca",
      "description": "Unauthorized boarding while at anchor. Items stolen from deck.",
      "reference": "REF-20260401-006"
    },
    {
      "date": "2026-04-01",
      "lat": 5.7624,
      "lng": 9.3037,
      "type": "Kidnapping",
      "region": "Nigeria Coast",
      "description": "Crew members taken. Authorities notified.",
      "reference": "REF-20260401-012"
    },
    {
      "date": "2026-03-29",
      "lat": 5.0568,
      "lng": 6.013,
      "type": "Kidnapping",
      "region": "Gulf of Guinea",
      "description": "Crew members taken. Authorities notified.",
      "reference": "REF-20260329-008"
    },
    {
      "date": "2026-03-26",
      "lat": 12.1371,
      "lng": 44.4102,
      "type": "Piracy",
      "region": "Gulf of Aden",
      "description": "Vessel approached by armed skiffs. Evasive maneuvers taken.",
      "reference": "REF-20260326-003"
    },
    {
      "date": "2026-03-21",
      "lat": 11.1897,
      "lng": 43.6032,
      "type": "Suspicious Approach",
      "region": "Gulf of Aden",
      "description": "Unknown vessels approached at high speed. Watchkeeping increased.",
      "reference": "REF-20260321-010"
    },
    {
      "date": "2026-03-17",
      "lat": 11.683,
      "lng": 113.2841,
      "type": "Harassment",
      "region": "South China Sea",
      "description": "Vessel harassed by military/paramilitary craft.",
      "reference": "REF-20260317-004"
    },
    {
      "date": "2026-03-17",
      "lat": 2.9927,
      "lng": 3.7045,
      "type": "Kidnapping",
      "region": "Gulf of Guinea",
      "description": "Crew members taken. Authorities notified.",
      "reference": "REF-20260317-005"
    },
    {
      "date": "2026-03-17",
      "lat": 14.473,
      "lng": 41.3557,
      "type": "Warning Shots",
      "region": "Red Sea",
      "description": "Warning shots fired across bow.",
      "reference": "REF-20260317-014"
    }
  ],
  "source": "Maritime Security Hotspot Data"
}