{
  "updated": "2026-02-07T13:55:55.616795",
  "incidents": [
    {
      "date": "2026-02-06",
      "lat": 5.9161,
      "lng": 50.6742,
      "type": "Hijacking",
      "region": "Somalia Coast",
      "description": "Vessel boarded and taken control of by armed persons.",
      "reference": "REF-20260206-011"
    },
    {
      "date": "2026-02-04",
      "lat": 3.369,
      "lng": 7.063,
      "type": "Piracy",
      "region": "Gulf of Guinea",
      "description": "Vessel approached by armed skiffs. Evasive maneuvers taken.",
      "reference": "REF-20260204-012"
    },
    {
      "date": "2026-01-28",
      "lat": 16.5842,
      "lng": 40.5866,
      "type": "Warning Shots",
      "region": "Red Sea",
      "description": "Warning shots fired across bow.",
      "reference": "REF-20260128-015"
    },
    {
      "date": "2026-01-23",
      "lat": 5.7551,
      "lng": 8.0859,
      "type": "Kidnapping",
      "region": "Nigeria Coast",
      "description": "Crew members taken. Authorities notified.",
      "reference": "REF-20260123-002"
    },
    {
      "date": "2026-01-19",
      "lat": 4.7675,
      "lng": 6.9101,
      "type": "Armed Robbery",
      "region": "Nigeria Coast",
      "description": "Unauthorized boarding while at anchor. Items stolen from deck.",
      "reference": "REF-20260119-008"
    },
    {
      "date": "2026-01-15",
      "lat": 3.0123,
      "lng": 100.2907,
      "type": "Armed Robbery",
      "region": "Strait of Malacca",
      "description": "Unauthorized boarding while at anchor. Items stolen from deck.",
      "reference": "REF-20260115-003"
    },
    {
      "date": "2026-01-15",
      "lat": 5.133,
      "lng": 52.6756,
      "type": "Hijacking",
      "region": "Somalia Coast",
      "description": "Vessel boarded and taken control of by armed persons.",
      "reference": "REF-20260115-007"
    },
    {
      "date": "2026-01-10",
      "lat": 7.4558,
      "lng": 51.2352,
      "type": "Piracy",
      "region": "Somalia Coast",
      "description": "Vessel approached by armed skiffs. Evasive maneuvers taken.",
      "reference": "REF-20260110-004"
    },
    {
      "date": "2026-01-08",
      "lat": 12.5306,
      "lng": 45.8801,
      "type": "Armed Robbery",
      "region": "Gulf of Aden",
      "description": "Unauthorized boarding while at anchor. Items stolen from deck.",
      "reference": "REF-20260108-006"
    },
    {
      "date": "2026-01-05",
      "lat": 1.3951,
      "lng": 100.8805,
      "type": "Theft",
      "region": "Strait of Malacca",
      "description": "Stores stolen from deck during hours of darkness.",
      "reference": "REF-20260105-014"
    },
    {
      "date": "2026-01-05",
      "lat": 7.8764,
      "lng": 51.9578,
      "type": "Hijacking",
      "region": "Somalia Coast",
      "description": "Vessel boarded and taken control of by armed persons.",
      "reference": "REF-20260105-016"
    },
    {
      "date": "2025-12-30",
      "lat": 1.5549,
      "lng": 103.296,
      "type": "Boarding",
      "region": "Singapore Strait",
      "description": "Unauthorized persons boarded vessel.",
      "reference": "REF-20251230-013"
    },
    {
      "date": "2025-12-27",
      "lat": 14.1412,
      "lng": 42.1105,
      "type": "Warning Shots",
      "region": "Red Sea",
      "description": "Warning shots fired across bow.",
      "reference": "REF-20251227-010"
    },
    {
      "date": "2025-12-23",
      "lat": 5.9268,
      "lng": 51.3384,
      "type": "Piracy",
      "region": "Somalia Coast",
      "description": "Vessel approached by armed skiffs. Evasive maneuvers taken.",
      "reference": "REF-20251223-009"
    },
    {
      "date": "2025-12-13",
      "lat": 9.2976,
      "lng": 112.3431,
      "type": "Suspicious Activity",
      "region": "South China Sea",
      "description": "Maritime security incident reported.",
      "reference": "REF-20251213-005"
    },
    {
      "date": "2025-12-12",
      "lat": 14.024,
      "lng": 44.2477,
      "type": "Armed Robbery",
      "region": "Gulf of Aden",
      "description": "Unauthorized boarding while at anchor. Items stolen from deck.",
      "reference": "REF-20251212-001"
    }
  ],
  "source": "Maritime Security Hotspot Data"
}