{
  "updated": "2026-07-04T15:06:58.059589",
  "incidents": [
    {
      "date": "2026-06-16",
      "lat": 2.2501,
      "lng": 98.9921,
      "type": "Armed Robbery",
      "region": "Strait of Malacca",
      "description": "Unauthorized boarding while at anchor. Items stolen from deck.",
      "reference": "REF-20260616-003"
    },
    {
      "date": "2026-06-16",
      "lat": 5.5745,
      "lng": 6.3059,
      "type": "Armed Robbery",
      "region": "Nigeria Coast",
      "description": "Unauthorized boarding while at anchor. Items stolen from deck.",
      "reference": "REF-20260616-006"
    },
    {
      "date": "2026-06-12",
      "lat": 11.6199,
      "lng": 46.8132,
      "type": "Armed Robbery",
      "region": "Gulf of Aden",
      "description": "Unauthorized boarding while at anchor. Items stolen from deck.",
      "reference": "REF-20260612-016"
    },
    {
      "date": "2026-06-10",
      "lat": 12.3533,
      "lng": 46.1128,
      "type": "Suspicious Approach",
      "region": "Gulf of Aden",
      "description": "Unknown vessels approached at high speed. Watchkeeping increased.",
      "reference": "REF-20260610-015"
    },
    {
      "date": "2026-06-06",
      "lat": 1.0694,
      "lng": 102.2728,
      "type": "Theft",
      "region": "Strait of Malacca",
      "description": "Stores stolen from deck during hours of darkness.",
      "reference": "REF-20260606-011"
    },
    {
      "date": "2026-06-01",
      "lat": 11.626,
      "lng": 114.9984,
      "type": "Suspicious Activity",
      "region": "South China Sea",
      "description": "Maritime security incident reported.",
      "reference": "REF-20260601-005"
    },
    {
      "date": "2026-05-28",
      "lat": 0.0131,
      "lng": 102.7085,
      "type": "Boarding",
      "region": "Singapore Strait",
      "description": "Unauthorized persons boarded vessel.",
      "reference": "REF-20260528-014"
    },
    {
      "date": "2026-05-26",
      "lat": 13.8251,
      "lng": 38.8213,
      "type": "Suspicious Approach",
      "region": "Red Sea",
      "description": "Unknown vessels approached at high speed. Watchkeeping increased.",
      "reference": "REF-20260526-002"
    },
    {
      "date": "2026-05-24",
      "lat": 1.7931,
      "lng": 99.024,
      "type": "Armed Robbery",
      "region": "Strait of Malacca",
      "description": "Unauthorized boarding while at anchor. Items stolen from deck.",
      "reference": "REF-20260524-008"
    },
    {
      "date": "2026-05-24",
      "lat": 5.4297,
      "lng": 7.691,
      "type": "Piracy",
      "region": "Gulf of Guinea",
      "description": "Vessel approached by armed skiffs. Evasive maneuvers taken.",
      "reference": "REF-20260524-012"
    },
    {
      "date": "2026-05-19",
      "lat": 16.1485,
      "lng": 41.4528,
      "type": "Warning Shots",
      "region": "Red Sea",
      "description": "Warning shots fired across bow.",
      "reference": "REF-20260519-010"
    },
    {
      "date": "2026-05-18",
      "lat": 5.4234,
      "lng": 5.3075,
      "type": "Piracy",
      "region": "Gulf of Guinea",
      "description": "Vessel approached by armed skiffs. Evasive maneuvers taken.",
      "reference": "REF-20260518-007"
    },
    {
      "date": "2026-05-17",
      "lat": 12.8884,
      "lng": 42.2228,
      "type": "Armed Robbery",
      "region": "Gulf of Aden",
      "description": "Unauthorized boarding while at anchor. Items stolen from deck.",
      "reference": "REF-20260517-004"
    },
    {
      "date": "2026-05-16",
      "lat": 9.1505,
      "lng": 112.3678,
      "type": "Suspicious Activity",
      "region": "South China Sea",
      "description": "Maritime security incident reported.",
      "reference": "REF-20260516-009"
    },
    {
      "date": "2026-05-16",
      "lat": 2.3178,
      "lng": 98.0057,
      "type": "Theft",
      "region": "Strait of Malacca",
      "description": "Stores stolen from deck during hours of darkness.",
      "reference": "REF-20260516-013"
    },
    {
      "date": "2026-05-07",
      "lat": 12.4143,
      "lng": 43.0408,
      "type": "Piracy",
      "region": "Gulf of Aden",
      "description": "Vessel approached by armed skiffs. Evasive maneuvers taken.",
      "reference": "REF-20260507-001"
    }
  ],
  "source": "Maritime Security Hotspot Data"
}