{
  "updated": "2026-07-12T22:52:16.728701",
  "incidents": [
    {
      "date": "2026-07-10",
      "lat": 7.4166,
      "lng": 48.2935,
      "type": "Hijacking",
      "region": "Somalia Coast",
      "description": "Vessel boarded and taken control of by armed persons.",
      "reference": "REF-20260710-004"
    },
    {
      "date": "2026-07-10",
      "lat": 4.1351,
      "lng": 7.6475,
      "type": "Kidnapping",
      "region": "Nigeria Coast",
      "description": "Crew members taken. Authorities notified.",
      "reference": "REF-20260710-012"
    },
    {
      "date": "2026-07-08",
      "lat": 4.8801,
      "lng": 50.6012,
      "type": "Piracy",
      "region": "Somalia Coast",
      "description": "Vessel approached by armed skiffs. Evasive maneuvers taken.",
      "reference": "REF-20260708-002"
    },
    {
      "date": "2026-07-06",
      "lat": 3.4594,
      "lng": 5.763,
      "type": "Kidnapping",
      "region": "Nigeria Coast",
      "description": "Crew members taken. Authorities notified.",
      "reference": "REF-20260706-005"
    },
    {
      "date": "2026-07-06",
      "lat": 14.5334,
      "lng": 40.1526,
      "type": "Warning Shots",
      "region": "Red Sea",
      "description": "Warning shots fired across bow.",
      "reference": "REF-20260706-007"
    },
    {
      "date": "2026-07-05",
      "lat": 14.4523,
      "lng": 41.6642,
      "type": "Warning Shots",
      "region": "Red Sea",
      "description": "Warning shots fired across bow.",
      "reference": "REF-20260705-001"
    },
    {
      "date": "2026-07-05",
      "lat": 14.2566,
      "lng": 42.3853,
      "type": "Suspicious Approach",
      "region": "Red Sea",
      "description": "Unknown vessels approached at high speed. Watchkeeping increased.",
      "reference": "REF-20260705-008"
    },
    {
      "date": "2026-07-05",
      "lat": 4.4567,
      "lng": 50.7719,
      "type": "Hijacking",
      "region": "Somalia Coast",
      "description": "Vessel boarded and taken control of by armed persons.",
      "reference": "REF-20260705-015"
    },
    {
      "date": "2026-07-02",
      "lat": 0.9547,
      "lng": 98.5346,
      "type": "Armed Robbery",
      "region": "Strait of Malacca",
      "description": "Unauthorized boarding while at anchor. Items stolen from deck.",
      "reference": "REF-20260702-006"
    },
    {
      "date": "2026-06-27",
      "lat": 2.948,
      "lng": 98.1175,
      "type": "Armed Robbery",
      "region": "Strait of Malacca",
      "description": "Unauthorized boarding while at anchor. Items stolen from deck.",
      "reference": "REF-20260627-010"
    },
    {
      "date": "2026-06-26",
      "lat": 4.1532,
      "lng": 8.9977,
      "type": "Kidnapping",
      "region": "Nigeria Coast",
      "description": "Crew members taken. Authorities notified.",
      "reference": "REF-20260626-009"
    },
    {
      "date": "2026-06-23",
      "lat": 16.16,
      "lng": 40.1623,
      "type": "Suspicious Approach",
      "region": "Red Sea",
      "description": "Unknown vessels approached at high speed. Watchkeeping increased.",
      "reference": "REF-20260623-011"
    },
    {
      "date": "2026-06-20",
      "lat": 8.5832,
      "lng": 111.5044,
      "type": "Harassment",
      "region": "South China Sea",
      "description": "Vessel harassed by military/paramilitary craft.",
      "reference": "REF-20260620-016"
    },
    {
      "date": "2026-06-16",
      "lat": 11.9457,
      "lng": 110.5211,
      "type": "Harassment",
      "region": "South China Sea",
      "description": "Vessel harassed by military/paramilitary craft.",
      "reference": "REF-20260616-003"
    },
    {
      "date": "2026-06-05",
      "lat": 2.9154,
      "lng": 103.7007,
      "type": "Theft",
      "region": "Strait of Malacca",
      "description": "Stores stolen from deck during hours of darkness.",
      "reference": "REF-20260605-013"
    },
    {
      "date": "2026-05-22",
      "lat": 10.286,
      "lng": 114.0032,
      "type": "Harassment",
      "region": "South China Sea",
      "description": "Vessel harassed by military/paramilitary craft.",
      "reference": "REF-20260522-014"
    }
  ],
  "source": "Maritime Security Hotspot Data"
}